[
  {
    "id": "teamSettings.lists",
    "defaultMessage": "Columns"
  },
  {
    "id": "teamSettings.metadata",
    "defaultMessage": "Annotation"
  },
  {
    "id": "teamSettings.tipline",
    "defaultMessage": "Tipline"
  },
  {
    "id": "teamSettings.data",
    "defaultMessage": "Data"
  },
  {
    "id": "teamSettings.tasks",
    "defaultMessage": "Tasks"
  },
  {
    "id": "teamSettings.rules",
    "defaultMessage": "Rules"
  },
  {
    "id": "teamSettings.Tags",
    "defaultMessage": "Tags"
  },
  {
    "id": "teamSettings.similarity",
    "defaultMessage": "Similarity"
  },
  {
    "id": "teamSettings.languages",
    "defaultMessage": "Languages"
  },
  {
    "id": "teamSettings.statuses",
    "defaultMessage": "Statuses"
  },
  {
    "id": "teamSettings.report",
    "defaultMessage": "Report"
  },
  {
    "id": "teamSettings.integrations",
    "defaultMessage": "Integrations"
  },
  {
    "id": "teamSettings.members",
    "defaultMessage": "Members"
  },
  {
    "id": "teamSettings.details",
    "defaultMessage": "Workspace details"
  }
]