[
  {
    "id": "singleChoiceTask.value",
    "defaultMessage": "Value"
  },
  {
    "id": "singleChoiceTask.other",
    "defaultMessage": "Other"
  },
  {
    "id": "singleChoiceTask.addValue",
    "description": "Button for creating a new entry to a list of selectable options",
    "defaultMessage": "Add Option"
  },
  {
    "id": "singleChoiceTask.addOther",
    "description": "Button for creating a new entry to a list of selectable options, in which the user is free to specify the value that will be selected",
    "defaultMessage": "Add \"Other\""
  }
]