[
  {
    "id": "passwordChange.newPassword",
    "defaultMessage": "New password"
  },
  {
    "id": "passwordChange.confirmPassword",
    "defaultMessage": "Confirm password"
  },
  {
    "id": "passwordChange.unmatchingPasswords",
    "defaultMessage": "Passwords didn't match"
  },
  {
    "id": "passwordChange.unknownError",
    "defaultMessage": "An unknown error has occurred. Please try again and contact {supportEmail} if the error persists."
  },
  {
    "id": "passwordChange.successTitle",
    "defaultMessage": "Password updated"
  },
  {
    "id": "passwordChange.successMsg",
    "defaultMessage": "You're all set. Now you can log in with your new password."
  },
  {
    "id": "passwordChange.signIn",
    "defaultMessage": "Got it"
  },
  {
    "id": "passwordChange.title",
    "defaultMessage": "Change password"
  }
]